{
  "openapi": "3.0.1",
  "info": {
    "title": "defaultTitle",
    "description": "defaultDescription",
    "version": "0.1"
  },
  "servers": [
    {
      "url": "https://meowfacts.herokuapp.com"
    }
  ],
  "paths": {
    "/": {
      "get": {
        "description": "Auto generated using Swagger Inspector",
        "operationId" : "facts",
        "parameters": [
          {
            "name": "count",
            "in": "query",
            "required": false,
            "style": "form",
            "explode": true,
            "schema": {
              "type": "string"
            },
            "example": "3"
          },
          {
            "name": "lang",
            "in": "query",
            "required": false,
            "style": "form",
            "explode": true,
            "schema": {
              "type": "string"
            },
            "example": "ukr"
          }
        ],
        "responses": {
          "200": {
            "description": "Auto generated using Swagger Inspector",
            "content": {
              "application/json; charset=utf-8": {
                "schema": {
                  "type": "string"
                },
                "examples": {}
              }
            }
          }
        },
        "servers": [
          {
            "url": "https://meowfacts.herokuapp.com"
          }
        ]
      },
      "servers": [
        {
          "url": "https://meowfacts.herokuapp.com"
        }
      ]
    }
  },
  "components": {}
}